{
  "36TDVdRgwobQmmgmIcArku": {
    "Key": "36TDVdRgwobQmmgmIcArku",
    "ItemStructName": "ItemData"
  },
  "79S6xV4311furJ876aNSCW": {
    "Key": "79S6xV4311furJ876aNSCW",
    "ItemStructName": "ItemData"
  },
  "1HFg3j1cDGUaRaIgZO6QD2": {
    "Key": "1HFg3j1cDGUaRaIgZO6QD2",
    "ItemStructName": "ItemData"
  },
  "3NS9Iebw1C0DGn6OV7GIuO": {
    "Key": "3NS9Iebw1C0DGn6OV7GIuO",
    "ItemStructName": "ItemData"
  },
  "1uosYiC1HMo0FcpAABwHo": {
    "Key": "1uosYiC1HMo0FcpAABwHo",
    "ItemStructName": "ItemData"
  },
  "3noOLCM0UfePNrIhldKkq": {
    "Key": "3noOLCM0UfePNrIhldKkq",
    "ItemStructName": "ItemData"
  },
  "30oEzvPCKJvlr5k4Cqi6pk": {
    "Key": "30oEzvPCKJvlr5k4Cqi6pk",
    "ItemStructName": "ItemData"
  },
  "4gaokRRtX0VuCTqKWX64XI": {
    "Key": "4gaokRRtX0VuCTqKWX64XI",
    "ItemStructName": "ItemData"
  },
  "7BL6RD9Ud4AQJUuKD9OjL6": {
    "Key": "7BL6RD9Ud4AQJUuKD9OjL6",
    "ItemStructName": "ItemData"
  },
  "7DE5xI5wOINMd74wW0iNQu": {
    "Key": "7DE5xI5wOINMd74wW0iNQu",
    "ItemStructName": "ItemData"
  },
  "7F75X3h1LBQxd837kZ89A0": {
    "Key": "7F75X3h1LBQxd837kZ89A0",
    "ItemStructName": "ItemData"
  },
  "7H052IrPkDgtiR5bL7D7JY": {
    "Key": "7H052IrPkDgtiR5bL7D7JY",
    "ItemStructName": "ItemData"
  },
  "7Xy8HbRSx91lHUYOi5GqG": {
    "Key": "7Xy8HbRSx91lHUYOi5GqG",
    "ItemStructName": "ItemData"
  },
  "9QxfN9B4j4vgrms3gXyHw": {
    "Key": "9QxfN9B4j4vgrms3gXyHw",
    "ItemStructName": "ItemData"
  },
  "2DkRH6dqlYEgSpG1YhHBB2": {
    "Key": "2DkRH6dqlYEgSpG1YhHBB2",
    "ItemStructName": "ItemData"
  },
  "3af5yNtGlAKYs5Mv6CaDdw": {
    "Key": "3af5yNtGlAKYs5Mv6CaDdw",
    "ItemStructName": "ItemData"
  },
  "BJxEcsWwQNQkzkMF5EKoK": {
    "Key": "BJxEcsWwQNQkzkMF5EKoK",
    "ItemStructName": "ItemData"
  },
  "2FdQoDLljzQR8JUcoERuzI": {
    "Key": "2FdQoDLljzQR8JUcoERuzI",
    "ItemStructName": "ItemData"
  },
  "2HWQNRQ5LSWozwFh8xj6xM": {
    "Key": "2HWQNRQ5LSWozwFh8xj6xM",
    "ItemStructName": "ItemData"
  },
  "IrvJ4vlM1s4cQrLWvvZrM": {
    "Key": "IrvJ4vlM1s4cQrLWvvZrM",
    "ItemStructName": "ItemData"
  },
  "KkunR0KCfPBVOT07EjQpc": {
    "Key": "KkunR0KCfPBVOT07EjQpc",
    "ItemStructName": "ItemData"
  },
  "MduNHDeZ6v4bNLryYZ0e8": {
    "Key": "MduNHDeZ6v4bNLryYZ0e8",
    "ItemStructName": "ItemData"
  },
  "32hEXHCDWw0KlE3JOu1Vmi": {
    "Key": "32hEXHCDWw0KlE3JOu1Vmi",
    "ItemStructName": "ItemData"
  },
  "4iToHC2WvSwKMIhJr99tHU": {
    "Key": "4iToHC2WvSwKMIhJr99tHU",
    "ItemStructName": "ItemData"
  },
  "7Mf3aGjmyKDgPhDOCesHj6": {
    "Key": "7Mf3aGjmyKDgPhDOCesHj6",
    "ItemStructName": "ItemData"
  },
  "F5wHAKqYEldjgKVjxZUv2": {
    "Key": "F5wHAKqYEldjgKVjxZUv2",
    "ItemStructName": "ItemData"
  },
  "GyvizQFnIF1l71qf7fpFA": {
    "Key": "GyvizQFnIF1l71qf7fpFA",
    "ItemStructName": "ItemData"
  },
  "34aDyVneHDnaCDEY6gW9Me": {
    "Key": "34aDyVneHDnaCDEY6gW9Me",
    "ItemStructName": "ItemData"
  },
  "3k6yBOFlRDmovy0tIFwWae": {
    "Key": "3k6yBOFlRDmovy0tIFwWae",
    "ItemStructName": "ItemData"
  },
  "7It4bD1eTbLVScbuGFtr1s": {
    "Key": "7It4bD1eTbLVScbuGFtr1s",
    "ItemStructName": "ItemData"
  },
  "7Km47sSAyOtt6TQab5aI8u": {
    "Key": "7Km47sSAyOtt6TQab5aI8u",
    "ItemStructName": "ItemData"
  },
  "1szX07z2wLfvkZbm5ppqa": {
    "Key": "1szX07z2wLfvkZbm5ppqa",
    "ItemStructName": "ItemData"
  },
  "3lz9B76HJ0hsPAdj53tqq": {
    "Key": "3lz9B76HJ0hsPAdj53tqq",
    "ItemStructName": "ItemData"
  },
  "3cY5RakMMIOWx9G2Kg2G92": {
    "Key": "3cY5RakMMIOWx9G2Kg2G92",
    "ItemStructName": "ItemData"
  },
  "3eR4ub1O5LqivNQ0JiUuuW": {
    "Key": "3eR4ub1O5LqivNQ0JiUuuW",
    "ItemStructName": "ItemData"
  },
  "5eyeS9e7cv7sGd9o9Vw00": {
    "Key": "5eyeS9e7cv7sGd9o9Vw00",
    "ItemStructName": "ItemData"
  },
  "2BrRnU5fgwna2dC8nGEtiC": {
    "Key": "2BrRnU5fgwna2dC8nGEtiC",
    "ItemStructName": "ItemData"
  },
  "F5wE8W5j0kQToFj4vwZlI": {
    "Key": "F5wE8W5j0kQToFj4vwZlI",
    "ItemStructName": "ItemData"
  },
  "2DkRJZ2Dgyfp62UiuiJe52": {
    "Key": "2DkRJZ2Dgyfp62UiuiJe52",
    "ItemStructName": "ItemData"
  },
  "3tX17XAENqTU2oIxkytMq8": {
    "Key": "3tX17XAENqTU2oIxkytMq8",
    "ItemStructName": "ItemData"
  },
  "9QxfdY9qxLHVjWSab8Mfg": {
    "Key": "9QxfdY9qxLHVjWSab8Mfg",
    "ItemStructName": "ItemData"
  },
  "BJxEAg2viiib9LSRqo5s8": {
    "Key": "BJxEAg2viiib9LSRqo5s8",
    "ItemStructName": "ItemData"
  },
  "DCwlwp8liINw6TnvvDmYy": {
    "Key": "DCwlwp8liINw6TnvvDmYy",
    "ItemStructName": "ItemData"
  },
  "IrvHeMEb6fGZbkOrEdr0a": {
    "Key": "IrvHeMEb6fGZbkOrEdr0a",
    "ItemStructName": "ItemData"
  },
  "Kkuqwv0vvC6QsslKzYu8m": {
    "Key": "Kkuqwv0vvC6QsslKzYu8m",
    "ItemStructName": "ItemData"
  },
  "MduIYato3xRxzdZ74OZEm": {
    "Key": "MduIYato3xRxzdZ74OZEm",
    "ItemStructName": "ItemData"
  },
  "XxrXYSLhsUhczxlzTfbsm": {
    "Key": "XxrXYSLhsUhczxlzTfbsm",
    "ItemStructName": "ItemData"
  },
  "1sza5rO6T3I9kgBxxiNvc": {
    "Key": "1sza5rO6T3I9kgBxxiNvc",
    "ItemStructName": "ItemData"
  },
  "3lz69I9S8hFZxgw3XWiXY": {
    "Key": "3lz69I9S8hFZxgw3XWiXY",
    "ItemStructName": "ItemData"
  },
  "5eyeIW6H6GU1w7MdqpH3w": {
    "Key": "5eyeIW6H6GU1w7MdqpH3w",
    "ItemStructName": "ItemData"
  },
  "7Xy9D4WxkUY5acKo4lqNM": {
    "Key": "7Xy9D4WxkUY5acKo4lqNM",
    "ItemStructName": "ItemData"
  },
  "9QxgPh6XImO4zf2PyCkXA": {
    "Key": "9QxgPh6XImO4zf2PyCkXA",
    "ItemStructName": "ItemData"
  },
  "BJxATlqWOScSvLPhfEMfw": {
    "Key": "BJxATlqWOScSvLPhfEMfw",
    "ItemStructName": "ItemData"
  },
  "DCwhR6I16OSB4BuIHXb4i": {
    "Key": "DCwhR6I16OSB4BuIHXb4i",
    "ItemStructName": "ItemData"
  },
  "F5wCcbt8qPm0Ip6vOxrZg": {
    "Key": "F5wCcbt8qPm0Ip6vOxrZg",
    "ItemStructName": "ItemData"
  },
  "3Ym6MMhDuiVJXJFk66Rk24": {
    "Key": "3Ym6MMhDuiVJXJFk66Rk24",
    "ItemStructName": "ItemData"
  },
  "1szWj8OyNdkNomE4Htsv2": {
    "Key": "1szWj8OyNdkNomE4Htsv2",
    "ItemStructName": "ItemData"
  },
  "3HnAfXGcJE8J55LmIS2Tho": {
    "Key": "3HnAfXGcJE8J55LmIS2Tho",
    "ItemStructName": "ItemData"
  },
  "3JgA96tDhCwQQfMbTdColc": {
    "Key": "3JgA96tDhCwQQfMbTdColc",
    "ItemStructName": "ItemData"
  },
  "1yeVAk4y5th3yZ2t8o65c8": {
    "Key": "1yeVAk4y5th3yZ2t8o65c8",
    "ItemStructName": "ItemData"
  },
  "20XUhFj3yzonmnmTT1y0LQ": {
    "Key": "20XUhFj3yzonmnmTT1y0LQ",
    "ItemStructName": "ItemData"
  },
  "22QU8UKRbsmOqtOjGW55mq": {
    "Key": "22QU8UKRbsmOqtOjGW55mq",
    "ItemStructName": "ItemData"
  },
  "24JTkH2u3o0rG41sLAUl96": {
    "Key": "24JTkH2u3o0rG41sLAUl96",
    "ItemStructName": "ItemData"
  },
  "26CTGLz36egdutPJjhzZrs": {
    "Key": "26CTGLz36egdutPJjhzZrs",
    "ItemStructName": "ItemData"
  },
  "285Sl1xdbw7zhzMQgtb0d6": {
    "Key": "285Sl1xdbw7zhzMQgtb0d6",
    "ItemStructName": "ItemData"
  },
  "29ySEEMMwfnTtzOM3cOYmO": {
    "Key": "29ySEEMMwfnTtzOM3cOYmO",
    "ItemStructName": "ItemData"
  },
  "ownCQAyjWIQKvkgdWNEWW": {
    "Key": "ownCQAyjWIQKvkgdWNEWW",
    "ItemStructName": "ItemData"
  },
  "qpmlBszd0thtuGdoEQwts": {
    "Key": "qpmlBszd0thtuGdoEQwts",
    "ItemStructName": "ItemData"
  },
  "1szZeICnQW0JXaHbBplMu": {
    "Key": "1szZeICnQW0JXaHbBplMu",
    "ItemStructName": "ItemData"
  },
  "1J8fboy3MPTNilPfwKIyzQ": {
    "Key": "1J8fboy3MPTNilPfwKIyzQ",
    "ItemStructName": "ItemData"
  },
  "1L1f8IGvGswEfKb3fMckWu": {
    "Key": "1L1f8IGvGswEfKb3fMckWu",
    "ItemStructName": "ItemData"
  },
  "1MuedoyMoWowF9xQx84YYy": {
    "Key": "1MuedoyMoWowF9xQx84YYy",
    "ItemStructName": "ItemData"
  },
  "1YEblTCVQ4rFUETLVDTjpg": {
    "Key": "1YEblTCVQ4rFUETLVDTjpg",
    "ItemStructName": "ItemData"
  },
  "5CfghwBqquvncnCDDApaz2": {
    "Key": "5CfghwBqquvncnCDDApaz2",
    "ItemStructName": "ItemData"
  },
  "3LZ9jZi42lDnlJ19D5P8HQ": {
    "Key": "3LZ9jZi42lDnlJ19D5P8HQ",
    "ItemStructName": "ItemData"
  },
  "bjqXskb1UVWxV93HiiCki": {
    "Key": "bjqXskb1UVWxV93HiiCki",
    "ItemStructName": "ItemData"
  },
  "5bCaYXkcnLxsvD8uEkCrQW": {
    "Key": "5bCaYXkcnLxsvD8uEkCrQW",
    "ItemStructName": "ItemData"
  },
  "BJxDGuz87rCEaRmCqVNxI": {
    "Key": "BJxDGuz87rCEaRmCqVNxI",
    "ItemStructName": "ItemData"
  },
  "QPtPIhzlfT0OaWMwxazTs": {
    "Key": "QPtPIhzlfT0OaWMwxazTs",
    "ItemStructName": "ItemData"
  },
  "32hEVcooTyvMHwFhUnDNdA": {
    "Key": "32hEVcooTyvMHwFhUnDNdA",
    "ItemStructName": "ItemData"
  },
  "IrvIgP9pFxxGFtf6cgNAe": {
    "Key": "IrvIgP9pFxxGFtf6cgNAe",
    "ItemStructName": "ItemData"
  },
  "7Xy9kPVfpy6Xp4oz84EMq": {
    "Key": "7Xy9kPVfpy6Xp4oz84EMq",
    "ItemStructName": "ItemData"
  },
  "1szZzGeZqzulBzOPy3SMq": {
    "Key": "1szZzGeZqzulBzOPy3SMq",
    "ItemStructName": "ItemData"
  },
  "3lz6XvvyKkSDE173CkHhY": {
    "Key": "3lz6XvvyKkSDE173CkHhY",
    "ItemStructName": "ItemData"
  },
  "5eyfvzqNwKMhauHLkEaky": {
    "Key": "5eyfvzqNwKMhauHLkEaky",
    "ItemStructName": "ItemData"
  },
  "7XyAKJmMthwzNobipwtjU": {
    "Key": "7XyAKJmMthwzNobipwtjU",
    "ItemStructName": "ItemData"
  },
  "9QxeeO8JyaZinfVr5Wg1g": {
    "Key": "9QxeeO8JyaZinfVr5Wg1g",
    "ItemStructName": "ItemData"
  },
  "BJxB56ujRjiDCXwYWQkQC": {
    "Key": "BJxB56ujRjiDCXwYWQkQC",
    "ItemStructName": "ItemData"
  },
  "5VXbuyIY0JAkPcx5fodxZI": {
    "Key": "5VXbuyIY0JAkPcx5fodxZI",
    "ItemStructName": "ItemData"
  },
  "3lz9Ecqv6iQKwiB3wbykK": {
    "Key": "3lz9Ecqv6iQKwiB3wbykK",
    "ItemStructName": "ItemData"
  },
  "5eydLHZ5PPRZNEbH6oOuW": {
    "Key": "5eydLHZ5PPRZNEbH6oOuW",
    "ItemStructName": "ItemData"
  },
  "7Xy9bdWtdiQXlBG2b6AQi": {
    "Key": "7Xy9bdWtdiQXlBG2b6AQi",
    "ItemStructName": "ItemData"
  },
  "9QxcXSGMtUFWxnsmw7NoW": {
    "Key": "9QxcXSGMtUFWxnsmw7NoW",
    "ItemStructName": "ItemData"
  },
  "BJxAkg7gyFuqWEg9zkUS0": {
    "Key": "BJxAkg7gyFuqWEg9zkUS0",
    "ItemStructName": "ItemData"
  },
  "DCwhcoKpmltRNG8XTXCLI": {
    "Key": "DCwhcoKpmltRNG8XTXCLI",
    "ItemStructName": "ItemData"
  },
  "F5wGYdYo126Iz9TzwCPLc": {
    "Key": "F5wGYdYo126Iz9TzwCPLc",
    "ItemStructName": "ItemData"
  },
  "Gyvm3Stvkqq3KvC6WhqeO": {
    "Key": "Gyvm3Stvkqq3KvC6WhqeO",
    "ItemStructName": "ItemData"
  },
  "IrvHBQuClKTocG0SXhxei": {
    "Key": "IrvHBQuClKTocG0SXhxei",
    "ItemStructName": "ItemData"
  },
  "KkuoxaLsXGxBFkVlEK1r6": {
    "Key": "KkuoxaLsXGxBFkVlEK1r6",
    "ItemStructName": "ItemData"
  },
  "MduK8VZ6o3Oj5S58soJdo": {
    "Key": "MduK8VZ6o3Oj5S58soJdo",
    "ItemStructName": "ItemData"
  },
  "OWtuBQdEgpHhYhQUbaBpA": {
    "Key": "OWtuBQdEgpHhYhQUbaBpA",
    "ItemStructName": "ItemData"
  },
  "QPtMDE4xXd4hfxhH1zAR6": {
    "Key": "QPtMDE4xXd4hfxhH1zAR6",
    "ItemStructName": "ItemData"
  },
  "SIssIAE0OIrMVL8fZTz9s": {
    "Key": "SIssIAE0OIrMVL8fZTz9s",
    "ItemStructName": "ItemData"
  },
  "UBsQcDeof6QCDFiIlBLSC": {
    "Key": "UBsQcDeof6QCDFiIlBLSC",
    "ItemStructName": "ItemData"
  },
  "W4rwJNopClSHO236krNMO": {
    "Key": "W4rwJNopClSHO236krNMO",
    "ItemStructName": "ItemData"
  },
  "XxrUPQwJqF0XnEGwbuMHw": {
    "Key": "XxrUPQwJqF0XnEGwbuMHw",
    "ItemStructName": "ItemData"
  },
  "Zqr1Zo8f0VjjN3G5qZ0fA": {
    "Key": "Zqr1Zo8f0VjjN3G5qZ0fA",
    "ItemStructName": "ItemData"
  },
  "1szZsr9NfsTPAA5aH55sm": {
    "Key": "1szZsr9NfsTPAA5aH55sm",
    "ItemStructName": "ItemData"
  },
  "3lz3FfyDNUZIllnROzYhM": {
    "Key": "3lz3FfyDNUZIllnROzYhM",
    "ItemStructName": "ItemData"
  },
  "5eyaMArF52UWdxmwJJU6y": {
    "Key": "5eyaMArF52UWdxmwJJU6y",
    "ItemStructName": "ItemData"
  },
  "7XyBsIumISwU1wAXFxYjQ": {
    "Key": "7XyBsIumISwU1wAXFxYjQ",
    "ItemStructName": "ItemData"
  },
  "9QxemSeocD2gJFWSM1McS": {
    "Key": "9QxemSeocD2gJFWSM1McS",
    "ItemStructName": "ItemData"
  },
  "BJxCRtxqeF3BKkcgOQwTY": {
    "Key": "BJxCRtxqeF3BKkcgOQwTY",
    "ItemStructName": "ItemData"
  },
  "DCwhHdKf1A6yZj1POtgjA": {
    "Key": "DCwhHdKf1A6yZj1POtgjA",
    "ItemStructName": "ItemData"
  },
  "F5wGF7eCwPSWUjHNHs5B2": {
    "Key": "F5wGF7eCwPSWUjHNHs5B2",
    "ItemStructName": "ItemData"
  },
  "Gyvk200CfOHHFv98m4wYy": {
    "Key": "Gyvk200CfOHHFv98m4wYy",
    "ItemStructName": "ItemData"
  },
  "IrvIxpHOLCNKqzNf2hJaK": {
    "Key": "IrvIxpHOLCNKqzNf2hJaK",
    "ItemStructName": "ItemData"
  },
  "KkuoBL2IGVHVKP4NNQa4u": {
    "Key": "KkuoBL2IGVHVKP4NNQa4u",
    "ItemStructName": "ItemData"
  },
  "MduK2eUZg0NBt8KOoRUDQ": {
    "Key": "MduK2eUZg0NBt8KOoRUDQ",
    "ItemStructName": "ItemData"
  },
  "OWtpDCtA72luWtapA5S40": {
    "Key": "OWtpDCtA72luWtapA5S40",
    "ItemStructName": "ItemData"
  },
  "557iZuLL92OXV6zWaczFgW": {
    "Key": "557iZuLL92OXV6zWaczFgW",
    "ItemStructName": "ItemData"
  },
  "570i4z1CLPi8ODhmUeBIie": {
    "Key": "570i4z1CLPi8ODhmUeBIie",
    "ItemStructName": "ItemData"
  },
  "58thbYuNASAxSrm0ecG2XQ": {
    "Key": "58thbYuNASAxSrm0ecG2XQ",
    "ItemStructName": "ItemData"
  },
  "5CfgithkxEhlmH1PujX3QW": {
    "Key": "5CfgithkxEhlmH1PujX3QW",
    "ItemStructName": "ItemData"
  },
  "5EYgEekEHF5bp9QkN3XoIK": {
    "Key": "5EYgEekEHF5bp9QkN3XoIK",
    "ItemStructName": "ItemData"
  },
  "5IKfJhB5pCDCQTjaSOax72": {
    "Key": "5IKfJhB5pCDCQTjaSOax72",
    "ItemStructName": "ItemData"
  },
  "5KDeqMbcJzla4KYGnEHOE4": {
    "Key": "5KDeqMbcJzla4KYGnEHOE4",
    "ItemStructName": "ItemData"
  },
  "5M6eKQR8koXeafsN1bxwnY": {
    "Key": "5M6eKQR8koXeafsN1bxwnY",
    "ItemStructName": "ItemData"
  },
  "5NzdqX2KFxMvYunk1HOOpM": {
    "Key": "5NzdqX2KFxMvYunk1HOOpM",
    "ItemStructName": "ItemData"
  },
  "5PsdNk01FRV6PEguGlmHYG": {
    "Key": "5PsdNk01FRV6PEguGlmHYG",
    "ItemStructName": "ItemData"
  },
  "5RlcwOs7nud4TA5xUlTXjE": {
    "Key": "5RlcwOs7nud4TA5xUlTXjE",
    "ItemStructName": "ItemData"
  },
  "5TecSVTiGEenpywTDLTvP6": {
    "Key": "5TecSVTiGEenpywTDLTvP6",
    "ItemStructName": "ItemData"
  },
  "5VXbvhsOTY1t6Uoh8JRRxo": {
    "Key": "5VXbvhsOTY1t6Uoh8JRRxo",
    "ItemStructName": "ItemData"
  },
  "5XQbTEjoJFouN4eEgrETE8": {
    "Key": "5XQbTEjoJFouN4eEgrETE8",
    "ItemStructName": "ItemData"
  },
  "5ZJaySF78b5hm4Znlz0Fw8": {
    "Key": "5ZJaySF78b5hm4Znlz0Fw8",
    "ItemStructName": "ItemData"
  },
  "3af5y0DOpHfmwCJQUAvQAK": {
    "Key": "3af5y0DOpHfmwCJQUAvQAK",
    "ItemStructName": "ItemData"
  },
  "3Wt6vFqjNg9VTvRctD9Uem": {
    "Key": "3Wt6vFqjNg9VTvRctD9Uem",
    "ItemStructName": "ItemData"
  },
  "3HnAhem8ty4KTQMY3iJRgW": {
    "Key": "3HnAhem8ty4KTQMY3iJRgW",
    "ItemStructName": "ItemData"
  },
  "3AFCaAaSrzkuCdUj0laBuq": {
    "Key": "3AFCaAaSrzkuCdUj0laBuq",
    "ItemStructName": "ItemData"
  },
  "3iD40wJOyUOxnAfsepJJjs": {
    "Key": "3iD40wJOyUOxnAfsepJJjs",
    "ItemStructName": "ItemData"
  },
  "3k63VsrwJtcDGZndSVirSK": {
    "Key": "3k63VsrwJtcDGZndSVirSK",
    "ItemStructName": "ItemData"
  },
  "36TDVj0OMbLcAXJxxhZjSC": {
    "Key": "36TDVj0OMbLcAXJxxhZjSC",
    "ItemStructName": "ItemData"
  },
  "3Ym6Om95JpoXMOHxkOb54S": {
    "Key": "3Ym6Om95JpoXMOHxkOb54S",
    "ItemStructName": "ItemData"
  },
  "3JgAC2VLFiYTHDazWET0Jk": {
    "Key": "3JgAC2VLFiYTHDazWET0Jk",
    "ItemStructName": "ItemData"
  },
  "3RE8Gy3KVolZnFnHRMqyvY": {
    "Key": "3RE8Gy3KVolZnFnHRMqyvY",
    "ItemStructName": "ItemData"
  },
  "3T77p46qxeuL0pVMXawMxE": {
    "Key": "3T77p46qxeuL0pVMXawMxE",
    "ItemStructName": "ItemData"
  },
  "3V07K0fOCzwx5Ei4fPU6tM": {
    "Key": "3V07K0fOCzwx5Ei4fPU6tM",
    "ItemStructName": "ItemData"
  },
  "3LZ9iPgpKhLoYS87V92920": {
    "Key": "3LZ9iPgpKhLoYS87V92920",
    "ItemStructName": "ItemData"
  },
  "3NS9GnzOCKmra3X2PpmM0O": {
    "Key": "3NS9GnzOCKmra3X2PpmM0O",
    "ItemStructName": "ItemData"
  },
  "3PL8kark5zb2vonrVS7Pc0": {
    "Key": "3PL8kark5zb2vonrVS7Pc0",
    "ItemStructName": "ItemData"
  },
  "3af5rfhaqky7Jn9QQm7q6q": {
    "Key": "3af5rfhaqky7Jn9QQm7q6q",
    "ItemStructName": "ItemData"
  },
  "3cY5Pc0SJHSzbcQpIky2lM": {
    "Key": "3cY5Pc0SJHSzbcQpIky2lM",
    "ItemStructName": "ItemData"
  },
  "3eR50q75nlO29zZoo3ihFY": {
    "Key": "3eR50q75nlO29zZoo3ihFY",
    "ItemStructName": "ItemData"
  },
  "3eR4vL3YAdfaHPohQt5Qv2": {
    "Key": "3eR4vL3YAdfaHPohQt5Qv2",
    "ItemStructName": "ItemData"
  },
  "3lz32G3WdhXbqC3RnTVZtg": {
    "Key": "3lz32G3WdhXbqC3RnTVZtg",
    "ItemStructName": "ItemData"
  },
  "3gK4Thh1YbMytD7tSCdasK": {
    "Key": "3gK4Thh1YbMytD7tSCdasK",
    "ItemStructName": "ItemData"
  },
  "34aE3Ng2XMPlHGU5u7GbDM": {
    "Key": "34aE3Ng2XMPlHGU5u7GbDM",
    "ItemStructName": "ItemData"
  },
  "3FuB9rKQONb04lJLMPo7rE": {
    "Key": "3FuB9rKQONb04lJLMPo7rE",
    "ItemStructName": "ItemData"
  },
  "3C8C3OdmUOpt6AG8CzwZGK": {
    "Key": "3C8C3OdmUOpt6AG8CzwZGK",
    "ItemStructName": "ItemData"
  },
  "3E1Bedp7Z2KCflNmHI2L9E": {
    "Key": "3E1Bedp7Z2KCflNmHI2L9E",
    "ItemStructName": "ItemData"
  },
  "3cY5ToD8Dyeph7FDPtGNP6": {
    "Key": "3cY5ToD8Dyeph7FDPtGNP6",
    "ItemStructName": "ItemData"
  },
  "3gK4RWTsAGgbRStgqp0LjM": {
    "Key": "3gK4RWTsAGgbRStgqp0LjM",
    "ItemStructName": "ItemData"
  },
  "3iD3yS9HIhiR6hDRSMV5FY": {
    "Key": "3iD3yS9HIhiR6hDRSMV5FY",
    "ItemStructName": "ItemData"
  },
  "3k63ZMibdb3T6pqVLXeW2K": {
    "Key": "3k63ZMibdb3T6pqVLXeW2K",
    "ItemStructName": "ItemData"
  },
  "3lz31j0SuaSlsOh0Gg5F3I": {
    "Key": "3lz31j0SuaSlsOh0Gg5F3I",
    "ItemStructName": "ItemData"
  },
  "3ns2bVYhNQNWSWISw7J5cW": {
    "Key": "3ns2bVYhNQNWSWISw7J5cW",
    "ItemStructName": "ItemData"
  },
  "3pl288z7JVebX1ogltvsem": {
    "Key": "3pl288z7JVebX1ogltvsem",
    "ItemStructName": "ItemData"
  },
  "3re1fw5iVESETlwTVTM1hI": {
    "Key": "3re1fw5iVESETlwTVTM1hI",
    "ItemStructName": "ItemData"
  },
  "3tX1D8iLIEHbgTsUA4ZoJs": {
    "Key": "3tX1D8iLIEHbgTsUA4ZoJs",
    "ItemStructName": "ItemData"
  },
  "3vQ0fCNzfpkAN32p1BbCqG": {
    "Key": "3vQ0fCNzfpkAN32p1BbCqG",
    "ItemStructName": "ItemData"
  },
  "3xJ0A6wNF58a3nyoH7AE1A": {
    "Key": "3xJ0A6wNF58a3nyoH7AE1A",
    "ItemStructName": "ItemData"
  },
  "3zBzmBYkgtI5xMKd5BuUlM": {
    "Key": "3zBzmBYkgtI5xMKd5BuUlM",
    "ItemStructName": "ItemData"
  },
  "414zGpXBQ0uFz7oOTWV7Qm": {
    "Key": "414zGpXBQ0uFz7oOTWV7Qm",
    "ItemStructName": "ItemData"
  },
  "42xymbWrHLjlhBgNg4keP2": {
    "Key": "42xymbWrHLjlhBgNg4keP2",
    "ItemStructName": "ItemData"
  },
  "44qyJExE60iRqD2u46XPqi": {
    "Key": "44qyJExE60iRqD2u46XPqi",
    "ItemStructName": "ItemData"
  },
  "46jxoQSpDmCWE2GpEgQ9nk": {
    "Key": "46jxoQSpDmCWE2GpEgQ9nk",
    "ItemStructName": "ItemData"
  },
  "48cxKCSV5721w68oREfgm0": {
    "Key": "48cxKCSV5721w68oREfgm0",
    "ItemStructName": "ItemData"
  },
  "4AVwuqRpSTl9uLkfYWTAum": {
    "Key": "4AVwuqRpSTl9uLkfYWTAum",
    "ItemStructName": "ItemData"
  },
  "4COwOczW6sOV8GAur590yG": {
    "Key": "4COwOczW6sOV8GAur590yG",
    "ItemStructName": "ItemData"
  },
  "4EHvygUs5W9jL9sZuUuQFM": {
    "Key": "4EHvygUs5W9jL9sZuUuQFM",
    "ItemStructName": "ItemData"
  },
  "4GAvQRvXAhgu20KLJzC4VU": {
    "Key": "4GAvQRvXAhgu20KLJzC4VU",
    "ItemStructName": "ItemData"
  },
  "4I3ux5LtzO8KjcHaFTRJPE": {
    "Key": "4I3ux5LtzO8KjcHaFTRJPE",
    "ItemStructName": "ItemData"
  },
  "4JwuTimJpQhWxiTTwqem7E": {
    "Key": "4JwuTimJpQhWxiTTwqem7E",
    "ItemStructName": "ItemData"
  },
  "4Lpu4uIVt2If4eRbObT4iW": {
    "Key": "4Lpu4uIVt2If4eRbObT4iW",
    "ItemStructName": "ItemData"
  },
  "4RUscn4nW0m82Rn4rObpfE": {
    "Key": "4RUscn4nW0m82Rn4rObpfE",
    "ItemStructName": "ItemData"
  },
  "4TNs5t0isxrMc07pTXLQVE": {
    "Key": "4TNs5t0isxrMc07pTXLQVE",
    "ItemStructName": "ItemData"
  },
  "DCwi8xsfdDg1lF5vHNNdw": {
    "Key": "DCwi8xsfdDg1lF5vHNNdw",
    "ItemStructName": "ItemData"
  },
  "F5wDp55XMkgHI1vWhOVzE": {
    "Key": "F5wDp55XMkgHI1vWhOVzE",
    "ItemStructName": "ItemData"
  },
  "GyvntsJCZsw0j1dVLwmUS": {
    "Key": "GyvntsJCZsw0j1dVLwmUS",
    "ItemStructName": "ItemData"
  },
  "IrvLOjvBvT3o9lAvi2Vay": {
    "Key": "IrvLOjvBvT3o9lAvi2Vay",
    "ItemStructName": "ItemData"
  },
  "KkumcdloJg7YJ1Z4XGVPc": {
    "Key": "KkumcdloJg7YJ1Z4XGVPc",
    "ItemStructName": "ItemData"
  },
  "MduIOczb30lwIoi6Q659E": {
    "Key": "MduIOczb30lwIoi6Q659E",
    "ItemStructName": "ItemData"
  },
  "OWtuRaKaZ0nWRcbJMuiaO": {
    "Key": "OWtuRaKaZ0nWRcbJMuiaO",
    "ItemStructName": "ItemData"
  },
  "QPtLbWJ0GXZ8PsKLkfzjk": {
    "Key": "QPtLbWJ0GXZ8PsKLkfzjk",
    "ItemStructName": "ItemData"
  },
  "SIstz6yvYgdPOeB7ISvnU": {
    "Key": "SIstz6yvYgdPOeB7ISvnU",
    "ItemStructName": "ItemData"
  },
  "UBsQlZq9o7Kxx4UwY2Hcu": {
    "Key": "UBsQlZq9o7Kxx4UwY2Hcu",
    "ItemStructName": "ItemData"
  },
  "W4rx6lcdFpq4QEJ9K7huS": {
    "Key": "W4rx6lcdFpq4QEJ9K7huS",
    "ItemStructName": "ItemData"
  },
  "XxrRmP5ofbUPbG08mdxsu": {
    "Key": "XxrRmP5ofbUPbG08mdxsu",
    "ItemStructName": "ItemData"
  },
  "Zqr2OjU4c1QBueWAVJ0KG": {
    "Key": "Zqr2OjU4c1QBueWAVJ0KG",
    "ItemStructName": "ItemData"
  },
  "bjqVan96ogDttOxnvX82y": {
    "Key": "bjqVan96ogDttOxnvX82y",
    "ItemStructName": "ItemData"
  },
  "dcq1MmijLqQsA8zBt1YkC": {
    "Key": "dcq1MmijLqQsA8zBt1YkC",
    "ItemStructName": "ItemData"
  },
  "fVpbAzwd7muFD3igZCooC": {
    "Key": "fVpbAzwd7muFD3igZCooC",
    "ItemStructName": "ItemData"
  },
  "hOp7oQMTAM6TJFcNwQHWC": {
    "Key": "hOp7oQMTAM6TJFcNwQHWC",
    "ItemStructName": "ItemData"
  },
  "jHoczvxgyY3hXnrgviLnU": {
    "Key": "jHoczvxgyY3hXnrgviLnU",
    "ItemStructName": "ItemData"
  },
  "lAo9dMNX17FvdzlOIvoVU": {
    "Key": "lAo9dMNX17FvdzlOIvoVU",
    "ItemStructName": "ItemData"
  },
  "n3ngGmnT4vaRYvGgd685g": {
    "Key": "n3ngGmnT4vaRYvGgd685g",
    "ItemStructName": "ItemData"
  },
  "1usW8fATmFmRcOsHfUIyVU": {
    "Key": "1usW8fATmFmRcOsHfUIyVU",
    "ItemStructName": "ItemData"
  },
  "5eydlRe1yk7M3mb76gDI0": {
    "Key": "5eydlRe1yk7M3mb76gDI0",
    "ItemStructName": "ItemData"
  },
  "7XyCjtEViKBUko5HsZNTs": {
    "Key": "7XyCjtEViKBUko5HsZNTs",
    "ItemStructName": "ItemData"
  },
  "9QxgGlvJz6K88LOcdyinY": {
    "Key": "9QxgGlvJz6K88LOcdyinY",
    "ItemStructName": "ItemData"
  },
  "5ilTHNy2i2a3BoaCs9RZEO": {
    "Key": "5ilTHNy2i2a3BoaCs9RZEO",
    "ItemStructName": "ItemData"
  },
  "5keSmyXqgawiDQJznSWbGi": {
    "Key": "5keSmyXqgawiDQJznSWbGi",
    "ItemStructName": "ItemData"
  },
  "1szb48shTGCA1Mcg1PmBE": {
    "Key": "1szb48shTGCA1Mcg1PmBE",
    "ItemStructName": "ItemData"
  },
  "3lz4z1AnVIgw6t5sZDaNM": {
    "Key": "3lz4z1AnVIgw6t5sZDaNM",
    "ItemStructName": "ItemData"
  },
  "5eycQLXfpXJIGlMAZDjiS": {
    "Key": "5eycQLXfpXJIGlMAZDjiS",
    "ItemStructName": "ItemData"
  },
  "7Xy9vXrvqLBsXTzDghZXE": {
    "Key": "7Xy9vXrvqLBsXTzDghZXE",
    "ItemStructName": "ItemData"
  },
  "9Qxhzw0BdD91WJAWDm5Am": {
    "Key": "9Qxhzw0BdD91WJAWDm5Am",
    "ItemStructName": "ItemData"
  },
  "BJxBFelDVdieMG41OTjv6": {
    "Key": "BJxBFelDVdieMG41OTjv6",
    "ItemStructName": "ItemData"
  },
  "DCwl2Y3soOWJVDxkGPD8a": {
    "Key": "DCwl2Y3soOWJVDxkGPD8a",
    "ItemStructName": "ItemData"
  },
  "F5wGHiPARoo1uhSQW6d9c": {
    "Key": "F5wGHiPARoo1uhSQW6d9c",
    "ItemStructName": "ItemData"
  },
  "GyvnoZp09bpIUWzz3tePw": {
    "Key": "GyvnoZp09bpIUWzz3tePw",
    "ItemStructName": "ItemData"
  },
  "30p9g5KCWQaw6Jiu7trcxs": {
    "Key": "30p9g5KCWQaw6Jiu7trcxs",
    "ItemStructName": "ItemData"
  },
  "IrvIl8MFW7BvUKQeKtro8": {
    "Key": "IrvIl8MFW7BvUKQeKtro8",
    "ItemStructName": "ItemData"
  },
  "KkumFm4seFJYcUCvDyglc": {
    "Key": "KkumFm4seFJYcUCvDyglc",
    "ItemStructName": "ItemData"
  },
  "MduKe4deEyTjoYnhVJZPk": {
    "Key": "MduKe4deEyTjoYnhVJZPk",
    "ItemStructName": "ItemData"
  },
  "2HWQLKIaYUZlknLymWKp5U": {
    "Key": "2HWQLKIaYUZlknLymWKp5U",
    "ItemStructName": "ItemData"
  },
  "OWtt2MnSd2Qxq7XDPc2xk": {
    "Key": "OWtt2MnSd2Qxq7XDPc2xk",
    "ItemStructName": "ItemData"
  },
  "QPtLzTLh8lkmBPSGc1Vdw": {
    "Key": "QPtLzTLh8lkmBPSGc1Vdw",
    "ItemStructName": "ItemData"
  },
  "1One85BEPLwWoiZgrDz6uG": {
    "Key": "1One85BEPLwWoiZgrDz6uG",
    "ItemStructName": "ItemData"
  },
  "1QgdhhcGsTIjWfjQ3uXj96": {
    "Key": "1QgdhhcGsTIjWfjQ3uXj96",
    "ItemStructName": "ItemData"
  },
  "1USckK3hzZLjUiD2S70ogS": {
    "Key": "1USckK3hzZLjUiD2S70ogS",
    "ItemStructName": "ItemData"
  },
  "1WLcIoEKtcspaGlyF1PUdk": {
    "Key": "1WLcIoEKtcspaGlyF1PUdk",
    "ItemStructName": "ItemData"
  },
  "29ySIiFHB9r4tPK7ra8CuW": {
    "Key": "29ySIiFHB9r4tPK7ra8CuW",
    "ItemStructName": "ItemData"
  },
  "2BrRnROI3beP25B1Nlrl4a": {
    "Key": "2BrRnROI3beP25B1Nlrl4a",
    "ItemStructName": "ItemData"
  },
  "1SZdCFIYDffsFjdlBss7M0": {
    "Key": "1SZdCFIYDffsFjdlBss7M0",
    "ItemStructName": "ItemData"
  },
  "1sza9NVw6xmQXHGpxofPE": {
    "Key": "1sza9NVw6xmQXHGpxofPE",
    "ItemStructName": "ItemData"
  },
  "SIsyE9QK7CNfClIzlovtA": {
    "Key": "SIsyE9QK7CNfClIzlovtA",
    "ItemStructName": "ItemData"
  },
  "UBsSxTFkFB3lnyhEi9CYS": {
    "Key": "UBsSxTFkFB3lnyhEi9CYS",
    "ItemStructName": "ItemData"
  },
  "W4s0UfZFAxfIQoShqc4si": {
    "Key": "W4s0UfZFAxfIQoShqc4si",
    "ItemStructName": "ItemData"
  },
  "3FudS7Vngu3MJaJEqaP8vQ": {
    "Key": "3FudS7Vngu3MJaJEqaP8vQ",
    "ItemStructName": "ItemData"
  },
  "3Hnd46DUM4uVhaEjwzM6uu": {
    "Key": "3Hnd46DUM4uVhaEjwzM6uu",
    "ItemStructName": "ItemData"
  },
  "3JgcXWywn7h5A01MxUBZ9U": {
    "Key": "3JgcXWywn7h5A01MxUBZ9U",
    "ItemStructName": "ItemData"
  },
  "2FdQoD8jnEJr86rIW98d8a": {
    "Key": "2FdQoD8jnEJr86rIW98d8a",
    "ItemStructName": "ItemData"
  },
  "1QiSysVg8St0OBrBr8RHlI": {
    "Key": "1QiSysVg8St0OBrBr8RHlI",
    "ItemStructName": "ItemData"
  },
  "1SbSYabcLWa8XsW1pKgAOu": {
    "Key": "1SbSYabcLWa8XsW1pKgAOu",
    "ItemStructName": "ItemData"
  },
  "qpmkodKgg7vQjLvfNwA2S": {
    "Key": "qpmkodKgg7vQjLvfNwA2S",
    "ItemStructName": "ItemData"
  },
  "3lz7nEFagi9s3OpXU1ILg": {
    "Key": "3lz7nEFagi9s3OpXU1ILg",
    "ItemStructName": "ItemData"
  },
  "5eyf1k04aySwk9HkONtYW": {
    "Key": "5eyf1k04aySwk9HkONtYW",
    "ItemStructName": "ItemData"
  },
  "7Xy6b7ZISJK9Vc6cEKhkm": {
    "Key": "7Xy6b7ZISJK9Vc6cEKhkm",
    "ItemStructName": "ItemData"
  },
  "9QxddRwcSgE3777GuxQNU": {
    "Key": "9QxddRwcSgE3777GuxQNU",
    "ItemStructName": "ItemData"
  },
  "BJxAV31tji950VlULfuu8": {
    "Key": "BJxAV31tji950VlULfuu8",
    "ItemStructName": "ItemData"
  },
  "DCwm5teTgRxmZQpH5pCUq": {
    "Key": "DCwm5teTgRxmZQpH5pCUq",
    "ItemStructName": "ItemData"
  },
  "F5wCrQxy8LB5sIS8Mp5Cy": {
    "Key": "F5wCrQxy8LB5sIS8Mp5Cy",
    "ItemStructName": "ItemData"
  },
  "GyvpHLSvuQJxCcE1V0l84": {
    "Key": "GyvpHLSvuQJxCcE1V0l84",
    "ItemStructName": "ItemData"
  },
  "IrvJ3Y9gFw1cgJZ3PnAOW": {
    "Key": "IrvJ3Y9gFw1cgJZ3PnAOW",
    "ItemStructName": "ItemData"
  },
  "KkullwxjN5SsZkBnLYSZs": {
    "Key": "KkullwxjN5SsZkBnLYSZs",
    "ItemStructName": "ItemData"
  },
  "MduN2fn63IuVNSUB9TDKi": {
    "Key": "MduN2fn63IuVNSUB9TDKi",
    "ItemStructName": "ItemData"
  },
  "OWtpxPQ1yIe65tjcUP67U": {
    "Key": "OWtpxPQ1yIe65tjcUP67U",
    "ItemStructName": "ItemData"
  },
  "QPtRl4ZpDeGTULiMPG2D2": {
    "Key": "QPtRl4ZpDeGTULiMPG2D2",
    "ItemStructName": "ItemData"
  },
  "1szaKd9YM2uCpaK4spb0a": {
    "Key": "1szaKd9YM2uCpaK4spb0a",
    "ItemStructName": "ItemData"
  },
  "3lz9SWVW8QOrvbIvtE4Ku": {
    "Key": "3lz9SWVW8QOrvbIvtE4Ku",
    "ItemStructName": "ItemData"
  },
  "BJx9uuNEOEyx4IpPoiXo0": {
    "Key": "BJx9uuNEOEyx4IpPoiXo0",
    "ItemStructName": "ItemData"
  },
  "9QxdFbZDiRCoUU0uTipuq": {
    "Key": "9QxdFbZDiRCoUU0uTipuq",
    "ItemStructName": "ItemData"
  },
  "BJxCZnW9cCMoFVcpqcK48": {
    "Key": "BJxCZnW9cCMoFVcpqcK48",
    "ItemStructName": "ItemData"
  },
  "DCwkxOC4uLR5EHTbOPG7s": {
    "Key": "DCwkxOC4uLR5EHTbOPG7s",
    "ItemStructName": "ItemData"
  },
  "F5wFtbc0PB6GJ9UIwKIjI": {
    "Key": "F5wFtbc0PB6GJ9UIwKIjI",
    "ItemStructName": "ItemData"
  },
  "F5wGT4YhaQQV5b1rg9pyq": {
    "Key": "F5wGT4YhaQQV5b1rg9pyq",
    "ItemStructName": "ItemData"
  },
  "MduIuSfw0BxXIVLy8TWi0": {
    "Key": "MduIuSfw0BxXIVLy8TWi0",
    "ItemStructName": "ItemData"
  },
  "OWts0PV3F6OsQa6Sjzats": {
    "Key": "OWts0PV3F6OsQa6Sjzats",
    "ItemStructName": "ItemData"
  },
  "QPtNCcdHY2tQbUDQOAknw": {
    "Key": "QPtNCcdHY2tQbUDQOAknw",
    "ItemStructName": "ItemData"
  },
  "SIsy9Yw2QxA1GWvpjBJce": {
    "Key": "SIsy9Yw2QxA1GWvpjBJce",
    "ItemStructName": "ItemData"
  },
  "UBsRLxfN99tefy8ezWOJs": {
    "Key": "UBsRLxfN99tefy8ezWOJs",
    "ItemStructName": "ItemData"
  },
  "1nLv0BBhp4cWVDhaS3dzKy": {
    "Key": "1nLv0BBhp4cWVDhaS3dzKy",
    "ItemStructName": "BalloonResource"
  },
  "1pEuWSEcqsY9iIO1X6ChXs": {
    "Key": "1pEuWSEcqsY9iIO1X6ChXs",
    "ItemStructName": "BalloonResource"
  }
}